Users/ziondev/.local/share/man/man1/evilurl.1
src/__init__.py
src/evilurl.py
src/unicode_combinations.json
evilurl-2.0.7.dist-info/LICENSE
evilurl-2.0.7.dist-info/METADATA
evilurl-2.0.7.dist-info/WHEEL
evilurl-2.0.7.dist-info/entry_points.txt
evilurl-2.0.7.dist-info/top_level.txt
evilurl-2.0.7.dist-info/RECORD
