Metadata-Version: 2.1
Name: evilurl
Version: 2.0.7
Summary: A tool for analyzing domains for the risk of IDN homograph attacks
Home-page: https://github.com/glaubermagal/evilurl
Author: Glauber Magal
Author-email: apt65@proton.me
Classifier: Programming Language :: Python :: 3
Classifier: License :: OSI Approved :: MIT License
Classifier: Operating System :: OS Independent
License-File: LICENSE
